[
  {
    "source_name": "ieichiba",
    "source_type": "akiya_portal",
    "prefecture": null,
    "city": null,
    "entry_url": "https://www.ieichiba.com/",
    "listing_strategy": "ieichiba_home",
    "detail_strategy": "ieichiba_detail",
    "status": "live",
    "priority": 1,
    "blocker": null
  },
  {
    "source_name": "yamakita_akiya",
    "source_type": "municipal_bank",
    "prefecture": "神奈川県",
    "city": "山北町",
    "entry_url": "https://www.town.yamakita.kanagawa.jp/category/13-1-2-0-0.html",
    "listing_strategy": "yamakita_listing",
    "detail_strategy": "yamakita_detail",
    "status": "live",
    "priority": 2,
    "blocker": null
  },
  {
    "source_name": "hanno_akiya",
    "source_type": "municipal_bank",
    "prefecture": "埼玉県",
    "city": "飯能市",
    "entry_url": "https://www.city.hanno.lg.jp/kurashi_seikatsukankyo/akiya_reform/akiyabank/3962.html",
    "listing_strategy": "hanno_listing",
    "detail_strategy": "hanno_detail",
    "status": "live",
    "priority": 3,
    "blocker": null
  },
  {
    "source_name": "saku_akiya",
    "source_type": "municipal_bank",
    "prefecture": "長野県",
    "city": "佐久市",
    "entry_url": "https://39ijyu.com/all.php?kubun=IE",
    "listing_strategy": "saku_listing",
    "detail_strategy": "saku_detail",
    "status": "live",
    "priority": 3,
    "blocker": null
  },
  {
    "source_name": "kamogawa_akiya",
    "source_type": "municipal_bank",
    "prefecture": "千葉県",
    "city": "鴨川市",
    "entry_url": "https://www.city.kamogawa.lg.jp/site/iju/list34-104.html",
    "listing_strategy": "kamogawa_listing",
    "detail_strategy": "kamogawa_detail",
    "status": "live",
    "priority": 3,
    "blocker": null
  },
  {
    "source_name": "chichibu_akiya",
    "source_type": "municipal_bank",
    "prefecture": "埼玉県",
    "city": null,
    "entry_url": "https://www.chichibuakiyabank.com/",
    "listing_strategy": "chichibu_listing",
    "detail_strategy": "chichibu_detail",
    "status": "live",
    "priority": 3,
    "blocker": null
  },
  {
    "source_name": "minamiboso_akiya",
    "source_type": "municipal_bank",
    "prefecture": "千葉県",
    "city": "南房総市",
    "entry_url": "https://www.minamibosocity-iju.jp/guide/house/vacant/",
    "listing_strategy": "minamiboso_listing",
    "detail_strategy": "minamiboso_detail",
    "status": "live",
    "priority": 3,
    "blocker": null
  },
  {
    "source_name": "sakuho_akiya",
    "source_type": "municipal_bank",
    "prefecture": "長野県",
    "city": "佐久穂町",
    "entry_url": "https://www.town.sakuho.nagano.jp/iju/live/index.html",
    "listing_strategy": "sakuho_listing",
    "detail_strategy": "sakuho_detail",
    "status": "live",
    "priority": 3,
    "blocker": null
  },
  {
    "source_name": "lifull_akiyabank",
    "source_type": "akiya_portal",
    "prefecture": null,
    "city": null,
    "entry_url": "https://www.homes.co.jp/akiyabank/",
    "listing_strategy": null,
    "detail_strategy": null,
    "status": "blocked",
    "priority": 4,
    "blocker": "Returns 403 to automated requests; needs browser automation or API reverse-engineering"
  },
  {
    "source_name": "athome_akiya",
    "source_type": "akiya_portal",
    "prefecture": null,
    "city": null,
    "entry_url": "https://www.akiya-athome.jp/",
    "listing_strategy": null,
    "detail_strategy": null,
    "status": "blocked",
    "priority": 5,
    "blocker": "Returns HTTP 403 to automated requests (verified 2026-03-16). Needs browser automation or API key."
  },
  {
    "source_name": "akiya_gateway",
    "source_type": "akiya_portal",
    "prefecture": null,
    "city": null,
    "entry_url": "https://akiya-gateway.jp/",
    "listing_strategy": null,
    "detail_strategy": null,
    "status": "blocked",
    "priority": 5,
    "blocker": "Domain DNS does not resolve (verified 2026-03-16). Site may be defunct or renamed."
  },
  {
    "source_name": "zero_estate",
    "source_type": "akiya_portal",
    "prefecture": null,
    "city": null,
    "entry_url": "https://zero.estate/",
    "listing_strategy": null,
    "detail_strategy": null,
    "status": "live",
    "priority": 4,
    "blocker": "parent entry — 47 per-prefecture source entries are live"
  },
  {
    "source_name": "zero_estate_hokkaido",
    "source_type": "akiya_portal",
    "prefecture": "北海道",
    "city": null,
    "entry_url": "https://zero.estate/category/zero/hokkaido/hokkaido/",
    "listing_strategy": "zero_estate_listing",
    "detail_strategy": "zero_estate_detail",
    "status": "live",
    "priority": 4,
    "blocker": null
  },
  {
    "source_name": "zero_estate_aomori",
    "source_type": "akiya_portal",
    "prefecture": "青森県",
    "city": null,
    "entry_url": "https://zero.estate/category/zero/tohoku/aomori/",
    "listing_strategy": "zero_estate_listing",
    "detail_strategy": "zero_estate_detail",
    "status": "live",
    "priority": 4,
    "blocker": null
  },
  {
    "source_name": "zero_estate_iwate",
    "source_type": "akiya_portal",
    "prefecture": "岩手県",
    "city": null,
    "entry_url": "https://zero.estate/category/zero/tohoku/iwate/",
    "listing_strategy": "zero_estate_listing",
    "detail_strategy": "zero_estate_detail",
    "status": "live",
    "priority": 4,
    "blocker": null
  },
  {
    "source_name": "zero_estate_miyagi",
    "source_type": "akiya_portal",
    "prefecture": "宮城県",
    "city": null,
    "entry_url": "https://zero.estate/category/zero/tohoku/miyagi/",
    "listing_strategy": "zero_estate_listing",
    "detail_strategy": "zero_estate_detail",
    "status": "live",
    "priority": 4,
    "blocker": null
  },
  {
    "source_name": "zero_estate_akita",
    "source_type": "akiya_portal",
    "prefecture": "秋田県",
    "city": null,
    "entry_url": "https://zero.estate/category/zero/tohoku/akita/",
    "listing_strategy": "zero_estate_listing",
    "detail_strategy": "zero_estate_detail",
    "status": "live",
    "priority": 4,
    "blocker": null
  },
  {
    "source_name": "zero_estate_yamagata",
    "source_type": "akiya_portal",
    "prefecture": "山形県",
    "city": null,
    "entry_url": "https://zero.estate/category/zero/tohoku/yamagata/",
    "listing_strategy": "zero_estate_listing",
    "detail_strategy": "zero_estate_detail",
    "status": "live",
    "priority": 4,
    "blocker": null
  },
  {
    "source_name": "zero_estate_fukushima",
    "source_type": "akiya_portal",
    "prefecture": "福島県",
    "city": null,
    "entry_url": "https://zero.estate/category/zero/tohoku/fukushima/",
    "listing_strategy": "zero_estate_listing",
    "detail_strategy": "zero_estate_detail",
    "status": "live",
    "priority": 4,
    "blocker": null
  },
  {
    "source_name": "zero_estate_ibaraki",
    "source_type": "akiya_portal",
    "prefecture": "茨城県",
    "city": null,
    "entry_url": "https://zero.estate/category/zero/kanto/ibaraki/",
    "listing_strategy": "zero_estate_listing",
    "detail_strategy": "zero_estate_detail",
    "status": "live",
    "priority": 4,
    "blocker": null
  },
  {
    "source_name": "zero_estate_tochigi",
    "source_type": "akiya_portal",
    "prefecture": "栃木県",
    "city": null,
    "entry_url": "https://zero.estate/category/zero/kanto/tochigi/",
    "listing_strategy": "zero_estate_listing",
    "detail_strategy": "zero_estate_detail",
    "status": "live",
    "priority": 4,
    "blocker": null
  },
  {
    "source_name": "zero_estate_gunma",
    "source_type": "akiya_portal",
    "prefecture": "群馬県",
    "city": null,
    "entry_url": "https://zero.estate/category/zero/kanto/gunma/",
    "listing_strategy": "zero_estate_listing",
    "detail_strategy": "zero_estate_detail",
    "status": "live",
    "priority": 4,
    "blocker": null
  },
  {
    "source_name": "zero_estate_saitama",
    "source_type": "akiya_portal",
    "prefecture": "埼玉県",
    "city": null,
    "entry_url": "https://zero.estate/category/zero/kanto/saitama/",
    "listing_strategy": "zero_estate_listing",
    "detail_strategy": "zero_estate_detail",
    "status": "live",
    "priority": 4,
    "blocker": null
  },
  {
    "source_name": "zero_estate_chiba",
    "source_type": "akiya_portal",
    "prefecture": "千葉県",
    "city": null,
    "entry_url": "https://zero.estate/category/zero/kanto/chiba/",
    "listing_strategy": "zero_estate_listing",
    "detail_strategy": "zero_estate_detail",
    "status": "live",
    "priority": 4,
    "blocker": null
  },
  {
    "source_name": "zero_estate_tokyo",
    "source_type": "akiya_portal",
    "prefecture": "東京都",
    "city": null,
    "entry_url": "https://zero.estate/category/zero/kanto/tokyo/",
    "listing_strategy": "zero_estate_listing",
    "detail_strategy": "zero_estate_detail",
    "status": "live",
    "priority": 4,
    "blocker": null
  },
  {
    "source_name": "zero_estate_kanagawa",
    "source_type": "akiya_portal",
    "prefecture": "神奈川県",
    "city": null,
    "entry_url": "https://zero.estate/category/zero/kanto/kanagawa/",
    "listing_strategy": "zero_estate_listing",
    "detail_strategy": "zero_estate_detail",
    "status": "live",
    "priority": 4,
    "blocker": null
  },
  {
    "source_name": "zero_estate_niigata",
    "source_type": "akiya_portal",
    "prefecture": "新潟県",
    "city": null,
    "entry_url": "https://zero.estate/category/zero/chubu/niigata/",
    "listing_strategy": "zero_estate_listing",
    "detail_strategy": "zero_estate_detail",
    "status": "live",
    "priority": 4,
    "blocker": null
  },
  {
    "source_name": "zero_estate_toyama",
    "source_type": "akiya_portal",
    "prefecture": "富山県",
    "city": null,
    "entry_url": "https://zero.estate/category/zero/chubu/toyama/",
    "listing_strategy": "zero_estate_listing",
    "detail_strategy": "zero_estate_detail",
    "status": "live",
    "priority": 4,
    "blocker": null
  },
  {
    "source_name": "zero_estate_ishikawa",
    "source_type": "akiya_portal",
    "prefecture": "石川県",
    "city": null,
    "entry_url": "https://zero.estate/category/zero/chubu/ishikawa/",
    "listing_strategy": "zero_estate_listing",
    "detail_strategy": "zero_estate_detail",
    "status": "live",
    "priority": 4,
    "blocker": null
  },
  {
    "source_name": "zero_estate_fukui",
    "source_type": "akiya_portal",
    "prefecture": "福井県",
    "city": null,
    "entry_url": "https://zero.estate/category/zero/chubu/fukui/",
    "listing_strategy": "zero_estate_listing",
    "detail_strategy": "zero_estate_detail",
    "status": "live",
    "priority": 4,
    "blocker": null
  },
  {
    "source_name": "zero_estate_yamanashi",
    "source_type": "akiya_portal",
    "prefecture": "山梨県",
    "city": null,
    "entry_url": "https://zero.estate/category/zero/koushinetsu/yamanashi/",
    "listing_strategy": "zero_estate_listing",
    "detail_strategy": "zero_estate_detail",
    "status": "live",
    "priority": 4,
    "blocker": null
  },
  {
    "source_name": "zero_estate_nagano",
    "source_type": "akiya_portal",
    "prefecture": "長野県",
    "city": null,
    "entry_url": "https://zero.estate/category/zero/koushinetsu/nagano/",
    "listing_strategy": "zero_estate_listing",
    "detail_strategy": "zero_estate_detail",
    "status": "live",
    "priority": 4,
    "blocker": null
  },
  {
    "source_name": "zero_estate_gifu",
    "source_type": "akiya_portal",
    "prefecture": "岐阜県",
    "city": null,
    "entry_url": "https://zero.estate/category/zero/chubu/gifu/",
    "listing_strategy": "zero_estate_listing",
    "detail_strategy": "zero_estate_detail",
    "status": "live",
    "priority": 4,
    "blocker": null
  },
  {
    "source_name": "zero_estate_shizuoka",
    "source_type": "akiya_portal",
    "prefecture": "静岡県",
    "city": null,
    "entry_url": "https://zero.estate/category/zero/chubu/shizuoka/",
    "listing_strategy": "zero_estate_listing",
    "detail_strategy": "zero_estate_detail",
    "status": "live",
    "priority": 4,
    "blocker": null
  },
  {
    "source_name": "zero_estate_aichi",
    "source_type": "akiya_portal",
    "prefecture": "愛知県",
    "city": null,
    "entry_url": "https://zero.estate/category/zero/chubu/aichi/",
    "listing_strategy": "zero_estate_listing",
    "detail_strategy": "zero_estate_detail",
    "status": "live",
    "priority": 4,
    "blocker": null
  },
  {
    "source_name": "zero_estate_mie",
    "source_type": "akiya_portal",
    "prefecture": "三重県",
    "city": null,
    "entry_url": "https://zero.estate/category/zero/kinki/mie/",
    "listing_strategy": "zero_estate_listing",
    "detail_strategy": "zero_estate_detail",
    "status": "live",
    "priority": 4,
    "blocker": null
  },
  {
    "source_name": "zero_estate_shiga",
    "source_type": "akiya_portal",
    "prefecture": "滋賀県",
    "city": null,
    "entry_url": "https://zero.estate/category/zero/kinki/shiga/",
    "listing_strategy": "zero_estate_listing",
    "detail_strategy": "zero_estate_detail",
    "status": "live",
    "priority": 4,
    "blocker": null
  },
  {
    "source_name": "zero_estate_kyoto",
    "source_type": "akiya_portal",
    "prefecture": "京都府",
    "city": null,
    "entry_url": "https://zero.estate/category/zero/kinki/kyoto/",
    "listing_strategy": "zero_estate_listing",
    "detail_strategy": "zero_estate_detail",
    "status": "live",
    "priority": 4,
    "blocker": null
  },
  {
    "source_name": "zero_estate_osaka",
    "source_type": "akiya_portal",
    "prefecture": "大阪府",
    "city": null,
    "entry_url": "https://zero.estate/category/zero/kinki/osaka/",
    "listing_strategy": "zero_estate_listing",
    "detail_strategy": "zero_estate_detail",
    "status": "live",
    "priority": 4,
    "blocker": null
  },
  {
    "source_name": "zero_estate_hyogo",
    "source_type": "akiya_portal",
    "prefecture": "兵庫県",
    "city": null,
    "entry_url": "https://zero.estate/category/zero/kinki/hyogo/",
    "listing_strategy": "zero_estate_listing",
    "detail_strategy": "zero_estate_detail",
    "status": "live",
    "priority": 4,
    "blocker": null
  },
  {
    "source_name": "zero_estate_nara",
    "source_type": "akiya_portal",
    "prefecture": "奈良県",
    "city": null,
    "entry_url": "https://zero.estate/category/zero/kinki/nara/",
    "listing_strategy": "zero_estate_listing",
    "detail_strategy": "zero_estate_detail",
    "status": "live",
    "priority": 4,
    "blocker": null
  },
  {
    "source_name": "zero_estate_wakayama",
    "source_type": "akiya_portal",
    "prefecture": "和歌山県",
    "city": null,
    "entry_url": "https://zero.estate/category/zero/kinki/wakayama/",
    "listing_strategy": "zero_estate_listing",
    "detail_strategy": "zero_estate_detail",
    "status": "live",
    "priority": 4,
    "blocker": null
  },
  {
    "source_name": "zero_estate_tottori",
    "source_type": "akiya_portal",
    "prefecture": "鳥取県",
    "city": null,
    "entry_url": "https://zero.estate/category/zero/chugoku/tottori/",
    "listing_strategy": "zero_estate_listing",
    "detail_strategy": "zero_estate_detail",
    "status": "live",
    "priority": 4,
    "blocker": null
  },
  {
    "source_name": "zero_estate_shimane",
    "source_type": "akiya_portal",
    "prefecture": "島根県",
    "city": null,
    "entry_url": "https://zero.estate/category/zero/chugoku/shimane/",
    "listing_strategy": "zero_estate_listing",
    "detail_strategy": "zero_estate_detail",
    "status": "live",
    "priority": 4,
    "blocker": null
  },
  {
    "source_name": "zero_estate_okayama",
    "source_type": "akiya_portal",
    "prefecture": "岡山県",
    "city": null,
    "entry_url": "https://zero.estate/category/zero/chugoku/okayama/",
    "listing_strategy": "zero_estate_listing",
    "detail_strategy": "zero_estate_detail",
    "status": "live",
    "priority": 4,
    "blocker": null
  },
  {
    "source_name": "zero_estate_hiroshima",
    "source_type": "akiya_portal",
    "prefecture": "広島県",
    "city": null,
    "entry_url": "https://zero.estate/category/zero/chugoku/hiroshima/",
    "listing_strategy": "zero_estate_listing",
    "detail_strategy": "zero_estate_detail",
    "status": "live",
    "priority": 4,
    "blocker": null
  },
  {
    "source_name": "zero_estate_yamaguchi",
    "source_type": "akiya_portal",
    "prefecture": "山口県",
    "city": null,
    "entry_url": "https://zero.estate/category/zero/chugoku/yamaguchi/",
    "listing_strategy": "zero_estate_listing",
    "detail_strategy": "zero_estate_detail",
    "status": "live",
    "priority": 4,
    "blocker": null
  },
  {
    "source_name": "zero_estate_tokushima",
    "source_type": "akiya_portal",
    "prefecture": "徳島県",
    "city": null,
    "entry_url": "https://zero.estate/category/zero/shikoku/tokushima/",
    "listing_strategy": "zero_estate_listing",
    "detail_strategy": "zero_estate_detail",
    "status": "live",
    "priority": 4,
    "blocker": null
  },
  {
    "source_name": "zero_estate_kagawa",
    "source_type": "akiya_portal",
    "prefecture": "香川県",
    "city": null,
    "entry_url": "https://zero.estate/category/zero/shikoku/kagawa/",
    "listing_strategy": "zero_estate_listing",
    "detail_strategy": "zero_estate_detail",
    "status": "live",
    "priority": 4,
    "blocker": null
  },
  {
    "source_name": "zero_estate_ehime",
    "source_type": "akiya_portal",
    "prefecture": "愛媛県",
    "city": null,
    "entry_url": "https://zero.estate/category/zero/shikoku/ehime/",
    "listing_strategy": "zero_estate_listing",
    "detail_strategy": "zero_estate_detail",
    "status": "live",
    "priority": 4,
    "blocker": null
  },
  {
    "source_name": "zero_estate_kochi",
    "source_type": "akiya_portal",
    "prefecture": "高知県",
    "city": null,
    "entry_url": "https://zero.estate/category/zero/shikoku/kochi/",
    "listing_strategy": "zero_estate_listing",
    "detail_strategy": "zero_estate_detail",
    "status": "live",
    "priority": 4,
    "blocker": null
  },
  {
    "source_name": "zero_estate_fukuoka",
    "source_type": "akiya_portal",
    "prefecture": "福岡県",
    "city": null,
    "entry_url": "https://zero.estate/category/zero/kyushu/fukuoka/",
    "listing_strategy": "zero_estate_listing",
    "detail_strategy": "zero_estate_detail",
    "status": "live",
    "priority": 4,
    "blocker": null
  },
  {
    "source_name": "zero_estate_saga",
    "source_type": "akiya_portal",
    "prefecture": "佐賀県",
    "city": null,
    "entry_url": "https://zero.estate/category/zero/kyushu/saga/",
    "listing_strategy": "zero_estate_listing",
    "detail_strategy": "zero_estate_detail",
    "status": "live",
    "priority": 4,
    "blocker": null
  },
  {
    "source_name": "zero_estate_nagasaki",
    "source_type": "akiya_portal",
    "prefecture": "長崎県",
    "city": null,
    "entry_url": "https://zero.estate/category/zero/kyushu/nagasaki/",
    "listing_strategy": "zero_estate_listing",
    "detail_strategy": "zero_estate_detail",
    "status": "live",
    "priority": 4,
    "blocker": null
  },
  {
    "source_name": "zero_estate_kumamoto",
    "source_type": "akiya_portal",
    "prefecture": "熊本県",
    "city": null,
    "entry_url": "https://zero.estate/category/zero/kyushu/kumamoto/",
    "listing_strategy": "zero_estate_listing",
    "detail_strategy": "zero_estate_detail",
    "status": "live",
    "priority": 4,
    "blocker": null
  },
  {
    "source_name": "zero_estate_oita",
    "source_type": "akiya_portal",
    "prefecture": "大分県",
    "city": null,
    "entry_url": "https://zero.estate/category/zero/kyushu/oita/",
    "listing_strategy": "zero_estate_listing",
    "detail_strategy": "zero_estate_detail",
    "status": "live",
    "priority": 4,
    "blocker": null
  },
  {
    "source_name": "zero_estate_miyazaki",
    "source_type": "akiya_portal",
    "prefecture": "宮崎県",
    "city": null,
    "entry_url": "https://zero.estate/category/zero/kyushu/miyazaki/",
    "listing_strategy": "zero_estate_listing",
    "detail_strategy": "zero_estate_detail",
    "status": "live",
    "priority": 4,
    "blocker": null
  },
  {
    "source_name": "zero_estate_kagoshima",
    "source_type": "akiya_portal",
    "prefecture": "鹿児島県",
    "city": null,
    "entry_url": "https://zero.estate/category/zero/kyushu/kagoshima/",
    "listing_strategy": "zero_estate_listing",
    "detail_strategy": "zero_estate_detail",
    "status": "live",
    "priority": 4,
    "blocker": null
  },
  {
    "source_name": "zero_estate_okinawa",
    "source_type": "akiya_portal",
    "prefecture": "沖縄県",
    "city": null,
    "entry_url": "https://zero.estate/category/zero/okinawa/okinawa/",
    "listing_strategy": "zero_estate_listing",
    "detail_strategy": "zero_estate_detail",
    "status": "live",
    "priority": 4,
    "blocker": null
  },
  {
    "source_name": "saihoku",
    "source_type": "akiya_portal",
    "prefecture": "埼玉県",
    "city": null,
    "entry_url": "https://akiyabank.saihoku-ijuu.com/",
    "listing_strategy": "saihoku_listing",
    "detail_strategy": "saihoku_detail",
    "status": "live",
    "priority": 4,
    "blocker": null
  },
  {
    "source_name": "tokigawa_akiya",
    "source_type": "municipal_bank",
    "prefecture": "埼玉県",
    "city": "ときがわ町",
    "entry_url": "https://www.town.tokigawa.lg.jp/info/1012",
    "listing_strategy": "tokigawa_listing",
    "detail_strategy": "tokigawa_detail",
    "status": "live",
    "priority": 4,
    "blocker": null
  },
  {
    "source_name": "jmty_estate",
    "source_type": "rent_portal",
    "prefecture": null,
    "city": null,
    "entry_url": "https://jmty.jp/all/est",
    "listing_strategy": null,
    "detail_strategy": null,
    "status": "planned",
    "priority": 6,
    "blocker": "Phase 2 — parser not implemented, feasibility not verified"
  },
  {
    "source_name": "suumo_rent",
    "source_type": "rent_portal",
    "prefecture": null,
    "city": null,
    "entry_url": "https://suumo.jp/chintai/",
    "listing_strategy": null,
    "detail_strategy": null,
    "status": "planned",
    "priority": 7,
    "blocker": "Phase 2 — browser-heavy JS rendering, needs careful robots.txt compliance"
  },
  {
    "source_name": "fudousan_japan",
    "source_type": "sale_portal",
    "prefecture": null,
    "city": null,
    "entry_url": "https://www.fudousan.or.jp/",
    "listing_strategy": null,
    "detail_strategy": null,
    "status": "planned",
    "priority": 6,
    "blocker": "Phase 2 — parser not implemented, feasibility not verified"
  }
]
